src/Categorize_CLI/__init__.py
src/Categorize_CLI/__main__.py
src/Categorize_CLI/__version__.py
src/Categorize_CLI/commands/__init__.py
src/Categorize_CLI/commands/ext.py
src/Categorize_CLI/commands/key.py
src/Categorize_CLI/commands/year.py
src/Categorize_CLI/common/__init__.py
src/Categorize_CLI/common/extensions.py
src/Categorize_CLI/common/utils.py
src/Categorize_CLI/services/__init__.py
src/Categorize_CLI/services/ext_functions.py
src/Categorize_CLI/services/key_functions.py
src/Categorize_CLI/services/year_functions.py
categorize_cli-1.0.0.dist-info/entry_points.txt
categorize_cli-1.0.0.dist-info/LICENSE.txt
categorize_cli-1.0.0.dist-info/WHEEL
categorize_cli-1.0.0.dist-info/METADATA
categorize_cli-1.0.0.dist-info/RECORD
