Metadata-Version: 2.1
Name: categorize-cli
Version: 1.0.0
Summary: Categorize-CLI is a command-line-tool made to help you categorize/organize files in a given directory
Home-page: https://github.com/Rohith-JN/Categorize-CLI
License: MIT
Keywords: organize,automation,CLI,categorize,file management
Author: Rohith Nambiar
Author-email: rohithnambiar04@gmail.com
Requires-Python: >=3.7,<4.0
Classifier: Development Status :: 4 - Beta
Classifier: Environment :: Console
Classifier: Intended Audience :: End Users/Desktop
Classifier: License :: OSI Approved :: MIT License
Classifier: Natural Language :: English
Classifier: Operating System :: Microsoft :: Windows
Classifier: Programming Language :: Python :: 3
Classifier: Programming Language :: Python :: 3.10
Classifier: Programming Language :: Python :: 3.7
Classifier: Programming Language :: Python :: 3.8
Classifier: Programming Language :: Python :: 3.9
Classifier: Topic :: Utilities
Requires-Dist: click (>=8.0.0)
Requires-Dist: colorama (>=0.4.4,<0.5.0)
Requires-Dist: progress (>=1.6,<2.0)
Project-URL: Changelog, https://github.com/Rohith-JN/Categorize-CLI/blob/main/CHANGELOG.md
Project-URL: Issues, https://github.com/Rohith-JN/Categorize-CLI/issues
Project-URL: Repository, https://github.com/Rohith-JN/Categorize-CLI
